{
  "version": "1",
  "cognitoConfig": {
    "identityPoolName": "amplifyauth66351295_identitypool_66351295",
    "allowUnauthenticatedIdentities": false,
    "resourceNameTruncated": "amplif66351295",
    "userPoolName": "amplifyauth66351295_userpool_66351295",
    "autoVerifiedAttributes": [
      "email"
    ],
    "mfaConfiguration": "OFF",
    "mfaTypes": [
      "SMS Text Message"
    ],
    "smsAuthenticationMessage": "Your authentication code is {####}",
    "smsVerificationMessage": "Your verification code is {####}",
    "emailVerificationSubject": "Your verification code",
    "emailVerificationMessage": "Your verification code is {####}",
    "defaultPasswordPolicy": true,
    "passwordPolicyMinLength": "6",
    "passwordPolicyCharacters": [],
    "requiredAttributes": [
      "email"
    ],
    "aliasAttributes": [],
    "userpoolClientGenerateSecret": false,
    "userpoolClientRefreshTokenValidity": 30,
    "userpoolClientWriteAttributes": [
      "email"
    ],
    "userpoolClientReadAttributes": [
      "email"
    ],
    "userpoolClientLambdaRole": "amplif66351295_userpoolclient_lambda_role",
    "userpoolClientSetAttributes": false,
    "sharedId": "66351295",
    "resourceName": "amplifyauth6635129566351295",
    "authSelections": "identityPoolAndUserPool",
    "useDefault": "manual",
    "thirdPartyAuth": false,
    "usernameAttributes": [
      "email"
    ],
    "userPoolGroups": false,
    "adminQueries": false,
    "triggers": {
      "PreSignup": [
        "custom"
      ]
    },
    "hostedUI": false,
    "userPoolGroupList": [],
    "serviceName": "Cognito",
    "usernameCaseSensitive": false,
    "useEnabledMfas": true
  }
}